suitable_django_autocomplete/README.md
suitable_django_autocomplete/__init__.py
suitable_django_autocomplete/examples.py
suitable_django_autocomplete/fields.py
suitable_django_autocomplete/views.py
suitable_django_autocomplete/widgets.py
suitable_django_autocomplete/static/suitable_django_autocomplete/autocomplete.js
suitable_django_autocomplete/templates/suitable_django_autocomplete/autocomplete.html
suitable_django_autocomplete-0.6.1.dist-info/METADATA
suitable_django_autocomplete-0.6.1.dist-info/WHEEL
suitable_django_autocomplete-0.6.1.dist-info/licenses/LICENSE
suitable_django_autocomplete-0.6.1.dist-info/RECORD
