Metadata-Version: 2.4
Name: suitable-django-autocomplete
Version: 0.6.1
Summary: A suitable Django autocomplete widget using web components
Project-URL: Homepage, https://github.com/suitable-adventures/suitable-django-autocomplete
Project-URL: Repository, https://github.com/suitable-adventures/suitable-django-autocomplete
Project-URL: Documentation, https://github.com/suitable-adventures/suitable-django-autocomplete#readme
Project-URL: Bug Tracker, https://github.com/suitable-adventures/suitable-django-autocomplete/issues
Author-email: Johan Valentini Jensen <johan@valentini.dk>
License: MIT
License-File: LICENSE
Keywords: autocomplete,django,forms,web-components,widget
Classifier: Development Status :: 4 - Beta
Classifier: Environment :: Web Environment
Classifier: Framework :: Django
Classifier: Framework :: Django :: 4.2
Classifier: Intended Audience :: Developers
Classifier: License :: OSI Approved :: MIT License
Classifier: Operating System :: OS Independent
Classifier: Programming Language :: Python
Classifier: Programming Language :: Python :: 3
Classifier: Programming Language :: Python :: 3.9
Classifier: Programming Language :: Python :: 3.10
Classifier: Programming Language :: Python :: 3.11
Classifier: Programming Language :: Python :: 3.12
Classifier: Topic :: Internet :: WWW/HTTP
Classifier: Topic :: Internet :: WWW/HTTP :: Dynamic Content
Classifier: Topic :: Software Development :: Libraries :: Python Modules
Requires-Python: >=3.9
Requires-Dist: django>=4.2
Provides-Extra: dev
Requires-Dist: pytest; extra == 'dev'
Requires-Dist: pytest-django; extra == 'dev'
